README.md
setup.py
src/motleydatetime/__init__.py
src/motleydatetime/helpers.py
src/motleydatetime/version.py
src/motleydatetime.egg-info/PKG-INFO
src/motleydatetime.egg-info/SOURCES.txt
src/motleydatetime.egg-info/dependency_links.txt
src/motleydatetime.egg-info/requires.txt
src/motleydatetime.egg-info/top_level.txt